<annotation>
	<folder>folder</folder>
	<filename>filename</filename>
	<path>path</path>
	<source>
		<database>dataset</database>
	</source>
	<size>
		<width>5184</width>
		<height>3456</height>
		<depth>3</depth>
	</size>
	<segmented>0</segmented>
	<object>
		<name>MR</name>
		<pose>Unspecified</pose>
		<truncated>0</truncated>
		<difficult>0</difficult>
		<bndbox>
			<xmin>3212</xmin>
			<ymin>810</ymin>
			<xmax>3401</xmax>
			<ymax>968</ymax>
		</bndbox>
	</object>
	<object>
		<name>MR</name>
		<pose>Unspecified</pose>
		<truncated>0</truncated>
		<difficult>0</difficult>
		<bndbox>
			<xmin>1281</xmin>
			<ymin>2009</ymin>
			<xmax>1428</xmax>
			<ymax>2217</ymax>
		</bndbox>
	</object>
	<object>
		<name>MR</name>
		<pose>Unspecified</pose>
		<truncated>0</truncated>
		<difficult>0</difficult>
		<bndbox>
			<xmin>1598</xmin>
			<ymin>2086</ymin>
			<xmax>1729</xmax>
			<ymax>2295</ymax>
		</bndbox>
	</object>
	<object>
		<name>WF</name>
		<pose>Unspecified</pose>
		<truncated>0</truncated>
		<difficult>0</difficult>
		<bndbox>
			<xmin>605</xmin>
			<ymin>1488</ymin>
			<xmax>648</xmax>
			<ymax>1527</ymax>
		</bndbox>
	</object>
	<object>
		<name>WF</name>
		<pose>Unspecified</pose>
		<truncated>0</truncated>
		<difficult>0</difficult>
		<bndbox>
			<xmin>2303</xmin>
			<ymin>2496</ymin>
			<xmax>2337</xmax>
			<ymax>2532</ymax>
		</bndbox>
	</object>
	<object>
		<name>WF</name>
		<pose>Unspecified</pose>
		<truncated>0</truncated>
		<difficult>0</difficult>
		<bndbox>
			<xmin>4418</xmin>
			<ymin>803</ymin>
			<xmax>4461</xmax>
			<ymax>850</ymax>
		</bndbox>
	</object>
</annotation>