<annotation>
	<folder>folder</folder>
	<filename>filename</filename>
	<path>path</path>
	<source>
		<database>dataset</database>
	</source>
	<size>
		<width>5184</width>
		<height>3456</height>
		<depth>3</depth>
	</size>
	<segmented>0</segmented>
	<object>
		<name>WF</name>
		<pose>Unspecified</pose>
		<truncated>0</truncated>
		<difficult>0</difficult>
		<bndbox>
			<xmin>2206</xmin>
			<ymin>1045</ymin>
			<xmax>2243</xmax>
			<ymax>1092</ymax>
		</bndbox>
	</object>
	<object>
		<name>WF</name>
		<pose>Unspecified</pose>
		<truncated>0</truncated>
		<difficult>0</difficult>
		<bndbox>
			<xmin>2266</xmin>
			<ymin>1201</ymin>
			<xmax>2314</xmax>
			<ymax>1242</ymax>
		</bndbox>
	</object>
	<object>
		<name>WF</name>
		<pose>Unspecified</pose>
		<truncated>0</truncated>
		<difficult>0</difficult>
		<bndbox>
			<xmin>2239</xmin>
			<ymin>1438</ymin>
			<xmax>2281</xmax>
			<ymax>1478</ymax>
		</bndbox>
	</object>
	<object>
		<name>WF</name>
		<pose>Unspecified</pose>
		<truncated>0</truncated>
		<difficult>0</difficult>
		<bndbox>
			<xmin>2829</xmin>
			<ymin>1457</ymin>
			<xmax>2874</xmax>
			<ymax>1498</ymax>
		</bndbox>
	</object>
	<object>
		<name>WF</name>
		<pose>Unspecified</pose>
		<truncated>0</truncated>
		<difficult>0</difficult>
		<bndbox>
			<xmin>2510</xmin>
			<ymin>1519</ymin>
			<xmax>2559</xmax>
			<ymax>1560</ymax>
		</bndbox>
	</object>
	<object>
		<name>WF</name>
		<pose>Unspecified</pose>
		<truncated>0</truncated>
		<difficult>0</difficult>
		<bndbox>
			<xmin>2438</xmin>
			<ymin>1049</ymin>
			<xmax>2478</xmax>
			<ymax>1091</ymax>
		</bndbox>
	</object>
	<object>
		<name>MR</name>
		<pose>Unspecified</pose>
		<truncated>0</truncated>
		<difficult>0</difficult>
		<bndbox>
			<xmin>2275</xmin>
			<ymin>1366</ymin>
			<xmax>2393</xmax>
			<ymax>1437</ymax>
		</bndbox>
	</object>
	<object>
		<name>WF</name>
		<pose>Unspecified</pose>
		<truncated>0</truncated>
		<difficult>0</difficult>
		<bndbox>
			<xmin>2992</xmin>
			<ymin>1050</ymin>
			<xmax>3034</xmax>
			<ymax>1096</ymax>
		</bndbox>
	</object>
	<object>
		<name>WF</name>
		<pose>Unspecified</pose>
		<truncated>0</truncated>
		<difficult>0</difficult>
		<bndbox>
			<xmin>3231</xmin>
			<ymin>942</ymin>
			<xmax>3274</xmax>
			<ymax>979</ymax>
		</bndbox>
	</object>
	<object>
		<name>WF</name>
		<pose>Unspecified</pose>
		<truncated>0</truncated>
		<difficult>0</difficult>
		<bndbox>
			<xmin>3034</xmin>
			<ymin>783</ymin>
			<xmax>3084</xmax>
			<ymax>826</ymax>
		</bndbox>
	</object>
	<object>
		<name>WF</name>
		<pose>Unspecified</pose>
		<truncated>0</truncated>
		<difficult>0</difficult>
		<bndbox>
			<xmin>2367</xmin>
			<ymin>611</ymin>
			<xmax>2411</xmax>
			<ymax>653</ymax>
		</bndbox>
	</object>
	<object>
		<name>WF</name>
		<pose>Unspecified</pose>
		<truncated>0</truncated>
		<difficult>0</difficult>
		<bndbox>
			<xmin>3423</xmin>
			<ymin>954</ymin>
			<xmax>3459</xmax>
			<ymax>984</ymax>
		</bndbox>
	</object>
	<object>
		<name>WF</name>
		<pose>Unspecified</pose>
		<truncated>0</truncated>
		<difficult>0</difficult>
		<bndbox>
			<xmin>3376</xmin>
			<ymin>1436</ymin>
			<xmax>3413</xmax>
			<ymax>1473</ymax>
		</bndbox>
	</object>
	<object>
		<name>WF</name>
		<pose>Unspecified</pose>
		<truncated>0</truncated>
		<difficult>0</difficult>
		<bndbox>
			<xmin>3669</xmin>
			<ymin>573</ymin>
			<xmax>3705</xmax>
			<ymax>608</ymax>
		</bndbox>
	</object>
	<object>
		<name>WF</name>
		<pose>Unspecified</pose>
		<truncated>0</truncated>
		<difficult>0</difficult>
		<bndbox>
			<xmin>3532</xmin>
			<ymin>481</ymin>
			<xmax>3573</xmax>
			<ymax>521</ymax>
		</bndbox>
	</object>
	<object>
		<name>WF</name>
		<pose>Unspecified</pose>
		<truncated>0</truncated>
		<difficult>0</difficult>
		<bndbox>
			<xmin>3761</xmin>
			<ymin>667</ymin>
			<xmax>3802</xmax>
			<ymax>699</ymax>
		</bndbox>
	</object>
	<object>
		<name>WF</name>
		<pose>Unspecified</pose>
		<truncated>0</truncated>
		<difficult>0</difficult>
		<bndbox>
			<xmin>3766</xmin>
			<ymin>699</ymin>
			<xmax>3809</xmax>
			<ymax>734</ymax>
		</bndbox>
	</object>
	<object>
		<name>WF</name>
		<pose>Unspecified</pose>
		<truncated>0</truncated>
		<difficult>0</difficult>
		<bndbox>
			<xmin>3752</xmin>
			<ymin>800</ymin>
			<xmax>3797</xmax>
			<ymax>847</ymax>
		</bndbox>
	</object>
	<object>
		<name>WF</name>
		<pose>Unspecified</pose>
		<truncated>0</truncated>
		<difficult>0</difficult>
		<bndbox>
			<xmin>3844</xmin>
			<ymin>1058</ymin>
			<xmax>3880</xmax>
			<ymax>1094</ymax>
		</bndbox>
	</object>
	<object>
		<name>WF</name>
		<pose>Unspecified</pose>
		<truncated>0</truncated>
		<difficult>0</difficult>
		<bndbox>
			<xmin>3531</xmin>
			<ymin>1476</ymin>
			<xmax>3574</xmax>
			<ymax>1516</ymax>
		</bndbox>
	</object>
	<object>
		<name>WF</name>
		<pose>Unspecified</pose>
		<truncated>0</truncated>
		<difficult>0</difficult>
		<bndbox>
			<xmin>4164</xmin>
			<ymin>1588</ymin>
			<xmax>4200</xmax>
			<ymax>1629</ymax>
		</bndbox>
	</object>
	<object>
		<name>WF</name>
		<pose>Unspecified</pose>
		<truncated>0</truncated>
		<difficult>0</difficult>
		<bndbox>
			<xmin>4205</xmin>
			<ymin>1591</ymin>
			<xmax>4230</xmax>
			<ymax>1634</ymax>
		</bndbox>
	</object>
	<object>
		<name>WF</name>
		<pose>Unspecified</pose>
		<truncated>0</truncated>
		<difficult>0</difficult>
		<bndbox>
			<xmin>4190</xmin>
			<ymin>1154</ymin>
			<xmax>4222</xmax>
			<ymax>1194</ymax>
		</bndbox>
	</object>
	<object>
		<name>WF</name>
		<pose>Unspecified</pose>
		<truncated>0</truncated>
		<difficult>0</difficult>
		<bndbox>
			<xmin>4155</xmin>
			<ymin>816</ymin>
			<xmax>4197</xmax>
			<ymax>857</ymax>
		</bndbox>
	</object>
	<object>
		<name>WF</name>
		<pose>Unspecified</pose>
		<truncated>0</truncated>
		<difficult>0</difficult>
		<bndbox>
			<xmin>4422</xmin>
			<ymin>576</ymin>
			<xmax>4466</xmax>
			<ymax>615</ymax>
		</bndbox>
	</object>
	<object>
		<name>WF</name>
		<pose>Unspecified</pose>
		<truncated>0</truncated>
		<difficult>0</difficult>
		<bndbox>
			<xmin>4298</xmin>
			<ymin>937</ymin>
			<xmax>4333</xmax>
			<ymax>964</ymax>
		</bndbox>
	</object>
	<object>
		<name>WF</name>
		<pose>Unspecified</pose>
		<truncated>0</truncated>
		<difficult>0</difficult>
		<bndbox>
			<xmin>4348</xmin>
			<ymin>974</ymin>
			<xmax>4392</xmax>
			<ymax>1022</ymax>
		</bndbox>
	</object>
	<object>
		<name>WF</name>
		<pose>Unspecified</pose>
		<truncated>0</truncated>
		<difficult>0</difficult>
		<bndbox>
			<xmin>4473</xmin>
			<ymin>1287</ymin>
			<xmax>4515</xmax>
			<ymax>1312</ymax>
		</bndbox>
	</object>
	<object>
		<name>WF</name>
		<pose>Unspecified</pose>
		<truncated>0</truncated>
		<difficult>0</difficult>
		<bndbox>
			<xmin>4488</xmin>
			<ymin>1567</ymin>
			<xmax>4536</xmax>
			<ymax>1598</ymax>
		</bndbox>
	</object>
	<object>
		<name>WF</name>
		<pose>Unspecified</pose>
		<truncated>0</truncated>
		<difficult>0</difficult>
		<bndbox>
			<xmin>4993</xmin>
			<ymin>1626</ymin>
			<xmax>5038</xmax>
			<ymax>1657</ymax>
		</bndbox>
	</object>
	<object>
		<name>WF</name>
		<pose>Unspecified</pose>
		<truncated>0</truncated>
		<difficult>0</difficult>
		<bndbox>
			<xmin>5062</xmin>
			<ymin>1012</ymin>
			<xmax>5095</xmax>
			<ymax>1040</ymax>
		</bndbox>
	</object>
	<object>
		<name>WF</name>
		<pose>Unspecified</pose>
		<truncated>0</truncated>
		<difficult>0</difficult>
		<bndbox>
			<xmin>5127</xmin>
			<ymin>943</ymin>
			<xmax>5162</xmax>
			<ymax>980</ymax>
		</bndbox>
	</object>
	<object>
		<name>WF</name>
		<pose>Unspecified</pose>
		<truncated>0</truncated>
		<difficult>0</difficult>
		<bndbox>
			<xmin>4457</xmin>
			<ymin>449</ymin>
			<xmax>4490</xmax>
			<ymax>486</ymax>
		</bndbox>
	</object>
	<object>
		<name>WF</name>
		<pose>Unspecified</pose>
		<truncated>0</truncated>
		<difficult>0</difficult>
		<bndbox>
			<xmin>5084</xmin>
			<ymin>800</ymin>
			<xmax>5123</xmax>
			<ymax>834</ymax>
		</bndbox>
	</object>
	<object>
		<name>WF</name>
		<pose>Unspecified</pose>
		<truncated>0</truncated>
		<difficult>0</difficult>
		<bndbox>
			<xmin>5145</xmin>
			<ymin>804</ymin>
			<xmax>5182</xmax>
			<ymax>828</ymax>
		</bndbox>
	</object>
	<object>
		<name>WF</name>
		<pose>Unspecified</pose>
		<truncated>0</truncated>
		<difficult>0</difficult>
		<bndbox>
			<xmin>805</xmin>
			<ymin>1776</ymin>
			<xmax>843</xmax>
			<ymax>1808</ymax>
		</bndbox>
	</object>
	<object>
		<name>WF</name>
		<pose>Unspecified</pose>
		<truncated>0</truncated>
		<difficult>0</difficult>
		<bndbox>
			<xmin>768</xmin>
			<ymin>2061</ymin>
			<xmax>818</xmax>
			<ymax>2112</ymax>
		</bndbox>
	</object>
	<object>
		<name>WF</name>
		<pose>Unspecified</pose>
		<truncated>0</truncated>
		<difficult>0</difficult>
		<bndbox>
			<xmin>1198</xmin>
			<ymin>2175</ymin>
			<xmax>1235</xmax>
			<ymax>2212</ymax>
		</bndbox>
	</object>
	<object>
		<name>WF</name>
		<pose>Unspecified</pose>
		<truncated>0</truncated>
		<difficult>0</difficult>
		<bndbox>
			<xmin>987</xmin>
			<ymin>2096</ymin>
			<xmax>1035</xmax>
			<ymax>2135</ymax>
		</bndbox>
	</object>
	<object>
		<name>WF</name>
		<pose>Unspecified</pose>
		<truncated>0</truncated>
		<difficult>0</difficult>
		<bndbox>
			<xmin>715</xmin>
			<ymin>2577</ymin>
			<xmax>757</xmax>
			<ymax>2618</ymax>
		</bndbox>
	</object>
	<object>
		<name>WF</name>
		<pose>Unspecified</pose>
		<truncated>0</truncated>
		<difficult>0</difficult>
		<bndbox>
			<xmin>1233</xmin>
			<ymin>2410</ymin>
			<xmax>1267</xmax>
			<ymax>2442</ymax>
		</bndbox>
	</object>
	<object>
		<name>WF</name>
		<pose>Unspecified</pose>
		<truncated>0</truncated>
		<difficult>0</difficult>
		<bndbox>
			<xmin>1240</xmin>
			<ymin>2439</ymin>
			<xmax>1273</xmax>
			<ymax>2468</ymax>
		</bndbox>
	</object>
	<object>
		<name>WF</name>
		<pose>Unspecified</pose>
		<truncated>0</truncated>
		<difficult>0</difficult>
		<bndbox>
			<xmin>1521</xmin>
			<ymin>2339</ymin>
			<xmax>1563</xmax>
			<ymax>2384</ymax>
		</bndbox>
	</object>
	<object>
		<name>WF</name>
		<pose>Unspecified</pose>
		<truncated>0</truncated>
		<difficult>0</difficult>
		<bndbox>
			<xmin>1339</xmin>
			<ymin>1981</ymin>
			<xmax>1383</xmax>
			<ymax>2015</ymax>
		</bndbox>
	</object>
	<object>
		<name>WF</name>
		<pose>Unspecified</pose>
		<truncated>0</truncated>
		<difficult>0</difficult>
		<bndbox>
			<xmin>1284</xmin>
			<ymin>1843</ymin>
			<xmax>1319</xmax>
			<ymax>1875</ymax>
		</bndbox>
	</object>
	<object>
		<name>WF</name>
		<pose>Unspecified</pose>
		<truncated>0</truncated>
		<difficult>0</difficult>
		<bndbox>
			<xmin>1156</xmin>
			<ymin>1736</ymin>
			<xmax>1197</xmax>
			<ymax>1760</ymax>
		</bndbox>
	</object>
	<object>
		<name>WF</name>
		<pose>Unspecified</pose>
		<truncated>0</truncated>
		<difficult>0</difficult>
		<bndbox>
			<xmin>1413</xmin>
			<ymin>1758</ymin>
			<xmax>1455</xmax>
			<ymax>1788</ymax>
		</bndbox>
	</object>
	<object>
		<name>WF</name>
		<pose>Unspecified</pose>
		<truncated>0</truncated>
		<difficult>0</difficult>
		<bndbox>
			<xmin>1470</xmin>
			<ymin>2026</ymin>
			<xmax>1509</xmax>
			<ymax>2061</ymax>
		</bndbox>
	</object>
	<object>
		<name>WF</name>
		<pose>Unspecified</pose>
		<truncated>0</truncated>
		<difficult>0</difficult>
		<bndbox>
			<xmin>1386</xmin>
			<ymin>2709</ymin>
			<xmax>1429</xmax>
			<ymax>2747</ymax>
		</bndbox>
	</object>
	<object>
		<name>WF</name>
		<pose>Unspecified</pose>
		<truncated>0</truncated>
		<difficult>0</difficult>
		<bndbox>
			<xmin>2203</xmin>
			<ymin>1703</ymin>
			<xmax>2247</xmax>
			<ymax>1735</ymax>
		</bndbox>
	</object>
	<object>
		<name>WF</name>
		<pose>Unspecified</pose>
		<truncated>0</truncated>
		<difficult>0</difficult>
		<bndbox>
			<xmin>2091</xmin>
			<ymin>1739</ymin>
			<xmax>2140</xmax>
			<ymax>1772</ymax>
		</bndbox>
	</object>
	<object>
		<name>WF</name>
		<pose>Unspecified</pose>
		<truncated>0</truncated>
		<difficult>0</difficult>
		<bndbox>
			<xmin>2112</xmin>
			<ymin>1653</ymin>
			<xmax>2155</xmax>
			<ymax>1683</ymax>
		</bndbox>
	</object>
	<object>
		<name>WF</name>
		<pose>Unspecified</pose>
		<truncated>0</truncated>
		<difficult>0</difficult>
		<bndbox>
			<xmin>1813</xmin>
			<ymin>1933</ymin>
			<xmax>1860</xmax>
			<ymax>1982</ymax>
		</bndbox>
	</object>
	<object>
		<name>WF</name>
		<pose>Unspecified</pose>
		<truncated>0</truncated>
		<difficult>0</difficult>
		<bndbox>
			<xmin>1988</xmin>
			<ymin>1851</ymin>
			<xmax>2034</xmax>
			<ymax>1886</ymax>
		</bndbox>
	</object>
	<object>
		<name>WF</name>
		<pose>Unspecified</pose>
		<truncated>0</truncated>
		<difficult>0</difficult>
		<bndbox>
			<xmin>2129</xmin>
			<ymin>1863</ymin>
			<xmax>2178</xmax>
			<ymax>1899</ymax>
		</bndbox>
	</object>
	<object>
		<name>WF</name>
		<pose>Unspecified</pose>
		<truncated>0</truncated>
		<difficult>0</difficult>
		<bndbox>
			<xmin>2354</xmin>
			<ymin>2129</ymin>
			<xmax>2399</xmax>
			<ymax>2170</ymax>
		</bndbox>
	</object>
	<object>
		<name>WF</name>
		<pose>Unspecified</pose>
		<truncated>0</truncated>
		<difficult>0</difficult>
		<bndbox>
			<xmin>1962</xmin>
			<ymin>2475</ymin>
			<xmax>2007</xmax>
			<ymax>2532</ymax>
		</bndbox>
	</object>
	<object>
		<name>WF</name>
		<pose>Unspecified</pose>
		<truncated>0</truncated>
		<difficult>0</difficult>
		<bndbox>
			<xmin>2185</xmin>
			<ymin>2689</ymin>
			<xmax>2221</xmax>
			<ymax>2730</ymax>
		</bndbox>
	</object>
	<object>
		<name>WF</name>
		<pose>Unspecified</pose>
		<truncated>0</truncated>
		<difficult>0</difficult>
		<bndbox>
			<xmin>2917</xmin>
			<ymin>2770</ymin>
			<xmax>2965</xmax>
			<ymax>2815</ymax>
		</bndbox>
	</object>
	<object>
		<name>WF</name>
		<pose>Unspecified</pose>
		<truncated>0</truncated>
		<difficult>0</difficult>
		<bndbox>
			<xmin>2992</xmin>
			<ymin>2423</ymin>
			<xmax>3036</xmax>
			<ymax>2456</ymax>
		</bndbox>
	</object>
	<object>
		<name>WF</name>
		<pose>Unspecified</pose>
		<truncated>0</truncated>
		<difficult>0</difficult>
		<bndbox>
			<xmin>2742</xmin>
			<ymin>2422</ymin>
			<xmax>2790</xmax>
			<ymax>2455</ymax>
		</bndbox>
	</object>
	<object>
		<name>WF</name>
		<pose>Unspecified</pose>
		<truncated>0</truncated>
		<difficult>0</difficult>
		<bndbox>
			<xmin>3372</xmin>
			<ymin>2609</ymin>
			<xmax>3411</xmax>
			<ymax>2651</ymax>
		</bndbox>
	</object>
	<object>
		<name>WF</name>
		<pose>Unspecified</pose>
		<truncated>0</truncated>
		<difficult>0</difficult>
		<bndbox>
			<xmin>3304</xmin>
			<ymin>2291</ymin>
			<xmax>3351</xmax>
			<ymax>2327</ymax>
		</bndbox>
	</object>
	<object>
		<name>WF</name>
		<pose>Unspecified</pose>
		<truncated>0</truncated>
		<difficult>0</difficult>
		<bndbox>
			<xmin>2436</xmin>
			<ymin>1876</ymin>
			<xmax>2482</xmax>
			<ymax>1919</ymax>
		</bndbox>
	</object>
	<object>
		<name>MR</name>
		<pose>Unspecified</pose>
		<truncated>0</truncated>
		<difficult>0</difficult>
		<bndbox>
			<xmin>2567</xmin>
			<ymin>1983</ymin>
			<xmax>2681</xmax>
			<ymax>2072</ymax>
		</bndbox>
	</object>
	<object>
		<name>WF</name>
		<pose>Unspecified</pose>
		<truncated>0</truncated>
		<difficult>0</difficult>
		<bndbox>
			<xmin>3217</xmin>
			<ymin>1847</ymin>
			<xmax>3256</xmax>
			<ymax>1884</ymax>
		</bndbox>
	</object>
	<object>
		<name>WF</name>
		<pose>Unspecified</pose>
		<truncated>0</truncated>
		<difficult>0</difficult>
		<bndbox>
			<xmin>3771</xmin>
			<ymin>1940</ymin>
			<xmax>3804</xmax>
			<ymax>1981</ymax>
		</bndbox>
	</object>
	<object>
		<name>WF</name>
		<pose>Unspecified</pose>
		<truncated>0</truncated>
		<difficult>0</difficult>
		<bndbox>
			<xmin>3691</xmin>
			<ymin>2086</ymin>
			<xmax>3735</xmax>
			<ymax>2131</ymax>
		</bndbox>
	</object>
	<object>
		<name>WF</name>
		<pose>Unspecified</pose>
		<truncated>0</truncated>
		<difficult>0</difficult>
		<bndbox>
			<xmin>3547</xmin>
			<ymin>2249</ymin>
			<xmax>3591</xmax>
			<ymax>2283</ymax>
		</bndbox>
	</object>
	<object>
		<name>WF</name>
		<pose>Unspecified</pose>
		<truncated>0</truncated>
		<difficult>0</difficult>
		<bndbox>
			<xmin>3755</xmin>
			<ymin>2117</ymin>
			<xmax>3791</xmax>
			<ymax>2154</ymax>
		</bndbox>
	</object>
	<object>
		<name>WF</name>
		<pose>Unspecified</pose>
		<truncated>0</truncated>
		<difficult>0</difficult>
		<bndbox>
			<xmin>3988</xmin>
			<ymin>2076</ymin>
			<xmax>4037</xmax>
			<ymax>2113</ymax>
		</bndbox>
	</object>
	<object>
		<name>WF</name>
		<pose>Unspecified</pose>
		<truncated>0</truncated>
		<difficult>0</difficult>
		<bndbox>
			<xmin>4026</xmin>
			<ymin>2116</ymin>
			<xmax>4074</xmax>
			<ymax>2145</ymax>
		</bndbox>
	</object>
	<object>
		<name>WF</name>
		<pose>Unspecified</pose>
		<truncated>0</truncated>
		<difficult>0</difficult>
		<bndbox>
			<xmin>3848</xmin>
			<ymin>2345</ymin>
			<xmax>3893</xmax>
			<ymax>2381</ymax>
		</bndbox>
	</object>
	<object>
		<name>WF</name>
		<pose>Unspecified</pose>
		<truncated>0</truncated>
		<difficult>0</difficult>
		<bndbox>
			<xmin>3857</xmin>
			<ymin>2409</ymin>
			<xmax>3889</xmax>
			<ymax>2443</ymax>
		</bndbox>
	</object>
	<object>
		<name>WF</name>
		<pose>Unspecified</pose>
		<truncated>0</truncated>
		<difficult>0</difficult>
		<bndbox>
			<xmin>3723</xmin>
			<ymin>2502</ymin>
			<xmax>3769</xmax>
			<ymax>2540</ymax>
		</bndbox>
	</object>
	<object>
		<name>WF</name>
		<pose>Unspecified</pose>
		<truncated>0</truncated>
		<difficult>0</difficult>
		<bndbox>
			<xmin>3974</xmin>
			<ymin>2554</ymin>
			<xmax>4023</xmax>
			<ymax>2596</ymax>
		</bndbox>
	</object>
	<object>
		<name>WF</name>
		<pose>Unspecified</pose>
		<truncated>0</truncated>
		<difficult>0</difficult>
		<bndbox>
			<xmin>4089</xmin>
			<ymin>2290</ymin>
			<xmax>4127</xmax>
			<ymax>2328</ymax>
		</bndbox>
	</object>
	<object>
		<name>WF</name>
		<pose>Unspecified</pose>
		<truncated>0</truncated>
		<difficult>0</difficult>
		<bndbox>
			<xmin>4249</xmin>
			<ymin>2389</ymin>
			<xmax>4281</xmax>
			<ymax>2430</ymax>
		</bndbox>
	</object>
	<object>
		<name>WF</name>
		<pose>Unspecified</pose>
		<truncated>0</truncated>
		<difficult>0</difficult>
		<bndbox>
			<xmin>4746</xmin>
			<ymin>1771</ymin>
			<xmax>4792</xmax>
			<ymax>1810</ymax>
		</bndbox>
	</object>
	<object>
		<name>WF</name>
		<pose>Unspecified</pose>
		<truncated>0</truncated>
		<difficult>0</difficult>
		<bndbox>
			<xmin>4755</xmin>
			<ymin>1836</ymin>
			<xmax>4794</xmax>
			<ymax>1866</ymax>
		</bndbox>
	</object>
	<object>
		<name>WF</name>
		<pose>Unspecified</pose>
		<truncated>0</truncated>
		<difficult>0</difficult>
		<bndbox>
			<xmin>4868</xmin>
			<ymin>2362</ymin>
			<xmax>4909</xmax>
			<ymax>2395</ymax>
		</bndbox>
	</object>
	<object>
		<name>WF</name>
		<pose>Unspecified</pose>
		<truncated>0</truncated>
		<difficult>0</difficult>
		<bndbox>
			<xmin>5038</xmin>
			<ymin>2264</ymin>
			<xmax>5079</xmax>
			<ymax>2311</ymax>
		</bndbox>
	</object>
	<object>
		<name>WF</name>
		<pose>Unspecified</pose>
		<truncated>0</truncated>
		<difficult>0</difficult>
		<bndbox>
			<xmin>5053</xmin>
			<ymin>2353</ymin>
			<xmax>5100</xmax>
			<ymax>2386</ymax>
		</bndbox>
	</object>
	<object>
		<name>WF</name>
		<pose>Unspecified</pose>
		<truncated>0</truncated>
		<difficult>0</difficult>
		<bndbox>
			<xmin>4836</xmin>
			<ymin>2645</ymin>
			<xmax>4880</xmax>
			<ymax>2687</ymax>
		</bndbox>
	</object>
	<object>
		<name>WF</name>
		<pose>Unspecified</pose>
		<truncated>0</truncated>
		<difficult>0</difficult>
		<bndbox>
			<xmin>3984</xmin>
			<ymin>2807</ymin>
			<xmax>4028</xmax>
			<ymax>2838</ymax>
		</bndbox>
	</object>
	<object>
		<name>WF</name>
		<pose>Unspecified</pose>
		<truncated>0</truncated>
		<difficult>0</difficult>
		<bndbox>
			<xmin>4007</xmin>
			<ymin>2843</ymin>
			<xmax>4043</xmax>
			<ymax>2879</ymax>
		</bndbox>
	</object>
	<object>
		<name>WF</name>
		<pose>Unspecified</pose>
		<truncated>0</truncated>
		<difficult>0</difficult>
		<bndbox>
			<xmin>4597</xmin>
			<ymin>2735</ymin>
			<xmax>4640</xmax>
			<ymax>2777</ymax>
		</bndbox>
	</object>
	<object>
		<name>WF</name>
		<pose>Unspecified</pose>
		<truncated>0</truncated>
		<difficult>0</difficult>
		<bndbox>
			<xmin>4996</xmin>
			<ymin>2717</ymin>
			<xmax>5045</xmax>
			<ymax>2756</ymax>
		</bndbox>
	</object>
	<object>
		<name>WF</name>
		<pose>Unspecified</pose>
		<truncated>0</truncated>
		<difficult>0</difficult>
		<bndbox>
			<xmin>4866</xmin>
			<ymin>2852</ymin>
			<xmax>4919</xmax>
			<ymax>2892</ymax>
		</bndbox>
	</object>
	<object>
		<name>MR</name>
		<pose>Unspecified</pose>
		<truncated>0</truncated>
		<difficult>0</difficult>
		<bndbox>
			<xmin>4083</xmin>
			<ymin>1887</ymin>
			<xmax>4229</xmax>
			<ymax>2004</ymax>
		</bndbox>
	</object>
	<object>
		<name>WF</name>
		<pose>Unspecified</pose>
		<truncated>0</truncated>
		<difficult>0</difficult>
		<bndbox>
			<xmin>1171</xmin>
			<ymin>1482</ymin>
			<xmax>1196</xmax>
			<ymax>1513</ymax>
		</bndbox>
	</object>
	<object>
		<name>WF</name>
		<pose>Unspecified</pose>
		<truncated>0</truncated>
		<difficult>0</difficult>
		<bndbox>
			<xmin>1193</xmin>
			<ymin>2574</ymin>
			<xmax>1217</xmax>
			<ymax>2598</ymax>
		</bndbox>
	</object>
	<object>
		<name>WF</name>
		<pose>Unspecified</pose>
		<truncated>0</truncated>
		<difficult>0</difficult>
		<bndbox>
			<xmin>2026</xmin>
			<ymin>1799</ymin>
			<xmax>2059</xmax>
			<ymax>1829</ymax>
		</bndbox>
	</object>
	<object>
		<name>WF</name>
		<pose>Unspecified</pose>
		<truncated>0</truncated>
		<difficult>0</difficult>
		<bndbox>
			<xmin>2203</xmin>
			<ymin>1596</ymin>
			<xmax>2234</xmax>
			<ymax>1629</ymax>
		</bndbox>
	</object>
	<object>
		<name>WF</name>
		<pose>Unspecified</pose>
		<truncated>0</truncated>
		<difficult>0</difficult>
		<bndbox>
			<xmin>3856</xmin>
			<ymin>1320</ymin>
			<xmax>3892</xmax>
			<ymax>1351</ymax>
		</bndbox>
	</object>
	<object>
		<name>WF</name>
		<pose>Unspecified</pose>
		<truncated>0</truncated>
		<difficult>0</difficult>
		<bndbox>
			<xmin>4369</xmin>
			<ymin>1632</ymin>
			<xmax>4405</xmax>
			<ymax>1665</ymax>
		</bndbox>
	</object>
	<object>
		<name>WF</name>
		<pose>Unspecified</pose>
		<truncated>0</truncated>
		<difficult>0</difficult>
		<bndbox>
			<xmin>4291</xmin>
			<ymin>959</ymin>
			<xmax>4329</xmax>
			<ymax>979</ymax>
		</bndbox>
	</object>
	<object>
		<name>WF</name>
		<pose>Unspecified</pose>
		<truncated>0</truncated>
		<difficult>0</difficult>
		<bndbox>
			<xmin>4131</xmin>
			<ymin>2868</ymin>
			<xmax>4165</xmax>
			<ymax>2910</ymax>
		</bndbox>
	</object>
	<object>
		<name>WF</name>
		<pose>Unspecified</pose>
		<truncated>0</truncated>
		<difficult>0</difficult>
		<bndbox>
			<xmin>625</xmin>
			<ymin>1151</ymin>
			<xmax>660</xmax>
			<ymax>1186</ymax>
		</bndbox>
	</object>
	<object>
		<name>WF</name>
		<pose>Unspecified</pose>
		<truncated>0</truncated>
		<difficult>0</difficult>
		<bndbox>
			<xmin>1037</xmin>
			<ymin>953</ymin>
			<xmax>1076</xmax>
			<ymax>978</ymax>
		</bndbox>
	</object>
	<object>
		<name>WF</name>
		<pose>Unspecified</pose>
		<truncated>0</truncated>
		<difficult>0</difficult>
		<bndbox>
			<xmin>1394</xmin>
			<ymin>578</ymin>
			<xmax>1431</xmax>
			<ymax>605</ymax>
		</bndbox>
	</object>
	<object>
		<name>WF</name>
		<pose>Unspecified</pose>
		<truncated>0</truncated>
		<difficult>0</difficult>
		<bndbox>
			<xmin>1487</xmin>
			<ymin>1135</ymin>
			<xmax>1519</xmax>
			<ymax>1167</ymax>
		</bndbox>
	</object>
	<object>
		<name>WF</name>
		<pose>Unspecified</pose>
		<truncated>0</truncated>
		<difficult>0</difficult>
		<bndbox>
			<xmin>3438</xmin>
			<ymin>2390</ymin>
			<xmax>3476</xmax>
			<ymax>2430</ymax>
		</bndbox>
	</object>
	<object>
		<name>MR</name>
		<pose>Unspecified</pose>
		<truncated>0</truncated>
		<difficult>0</difficult>
		<bndbox>
			<xmin>1150</xmin>
			<ymin>399</ymin>
			<xmax>1265</xmax>
			<ymax>483</ymax>
		</bndbox>
	</object>
	<object>
		<name>MR</name>
		<pose>Unspecified</pose>
		<truncated>0</truncated>
		<difficult>0</difficult>
		<bndbox>
			<xmin>2246</xmin>
			<ymin>2484</ymin>
			<xmax>2437</xmax>
			<ymax>2597</ymax>
		</bndbox>
	</object>
	<object>
		<name>MR</name>
		<pose>Unspecified</pose>
		<truncated>0</truncated>
		<difficult>0</difficult>
		<bndbox>
			<xmin>4909</xmin>
			<ymin>426</ymin>
			<xmax>5028</xmax>
			<ymax>465</ymax>
		</bndbox>
	</object>
</annotation>