<annotation>
	<folder>folder</folder>
	<filename>filename</filename>
	<path>path</path>
	<source>
		<database>dataset</database>
	</source>
	<size>
		<width>5184</width>
		<height>3456</height>
		<depth>3</depth>
	</size>
	<segmented>0</segmented>
	<object>
		<name>MR</name>
		<pose>Unspecified</pose>
		<truncated>0</truncated>
		<difficult>0</difficult>
		<bndbox>
			<xmin>1865</xmin>
			<ymin>1300</ymin>
			<xmax>2057</xmax>
			<ymax>1449</ymax>
		</bndbox>
	</object>
	<object>
		<name>WF</name>
		<pose>Unspecified</pose>
		<truncated>0</truncated>
		<difficult>0</difficult>
		<bndbox>
			<xmin>5083</xmin>
			<ymin>1596</ymin>
			<xmax>5134</xmax>
			<ymax>1639</ymax>
		</bndbox>
	</object>
	<object>
		<name>WF</name>
		<pose>Unspecified</pose>
		<truncated>0</truncated>
		<difficult>0</difficult>
		<bndbox>
			<xmin>5058</xmin>
			<ymin>1080</ymin>
			<xmax>5105</xmax>
			<ymax>1122</ymax>
		</bndbox>
	</object>
	<object>
		<name>WF</name>
		<pose>Unspecified</pose>
		<truncated>0</truncated>
		<difficult>0</difficult>
		<bndbox>
			<xmin>5052</xmin>
			<ymin>1337</ymin>
			<xmax>5096</xmax>
			<ymax>1386</ymax>
		</bndbox>
	</object>
	<object>
		<name>WF</name>
		<pose>Unspecified</pose>
		<truncated>0</truncated>
		<difficult>0</difficult>
		<bndbox>
			<xmin>2246</xmin>
			<ymin>1774</ymin>
			<xmax>2293</xmax>
			<ymax>1827</ymax>
		</bndbox>
	</object>
	<object>
		<name>WF</name>
		<pose>Unspecified</pose>
		<truncated>0</truncated>
		<difficult>0</difficult>
		<bndbox>
			<xmin>2550</xmin>
			<ymin>2620</ymin>
			<xmax>2597</xmax>
			<ymax>2669</ymax>
		</bndbox>
	</object>
	<object>
		<name>WF</name>
		<pose>Unspecified</pose>
		<truncated>0</truncated>
		<difficult>0</difficult>
		<bndbox>
			<xmin>3010</xmin>
			<ymin>2733</ymin>
			<xmax>3053</xmax>
			<ymax>2778</ymax>
		</bndbox>
	</object>
	<object>
		<name>WF</name>
		<pose>Unspecified</pose>
		<truncated>0</truncated>
		<difficult>0</difficult>
		<bndbox>
			<xmin>3636</xmin>
			<ymin>2450</ymin>
			<xmax>3693</xmax>
			<ymax>2495</ymax>
		</bndbox>
	</object>
	<object>
		<name>WF</name>
		<pose>Unspecified</pose>
		<truncated>0</truncated>
		<difficult>0</difficult>
		<bndbox>
			<xmin>4083</xmin>
			<ymin>1850</ymin>
			<xmax>4125</xmax>
			<ymax>1890</ymax>
		</bndbox>
	</object>
	<object>
		<name>WF</name>
		<pose>Unspecified</pose>
		<truncated>0</truncated>
		<difficult>0</difficult>
		<bndbox>
			<xmin>1334</xmin>
			<ymin>1576</ymin>
			<xmax>1372</xmax>
			<ymax>1616</ymax>
		</bndbox>
	</object>
	<object>
		<name>WF</name>
		<pose>Unspecified</pose>
		<truncated>0</truncated>
		<difficult>0</difficult>
		<bndbox>
			<xmin>2110</xmin>
			<ymin>2077</ymin>
			<xmax>2148</xmax>
			<ymax>2114</ymax>
		</bndbox>
	</object>
	<object>
		<name>MR</name>
		<pose>Unspecified</pose>
		<truncated>0</truncated>
		<difficult>0</difficult>
		<bndbox>
			<xmin>670</xmin>
			<ymin>2473</ymin>
			<xmax>831</xmax>
			<ymax>2612</ymax>
		</bndbox>
	</object>
	<object>
		<name>WF</name>
		<pose>Unspecified</pose>
		<truncated>0</truncated>
		<difficult>0</difficult>
		<bndbox>
			<xmin>223</xmin>
			<ymin>2339</ymin>
			<xmax>246</xmax>
			<ymax>2367</ymax>
		</bndbox>
	</object>
</annotation>