<annotation>
	<folder>folder</folder>
	<filename>filename</filename>
	<path>path</path>
	<source>
		<database>dataset</database>
	</source>
	<size>
		<width>5184</width>
		<height>3456</height>
		<depth>3</depth>
	</size>
	<segmented>0</segmented>
	<object>
		<name>WF</name>
		<pose>Unspecified</pose>
		<truncated>0</truncated>
		<difficult>0</difficult>
		<bndbox>
			<xmin>324</xmin>
			<ymin>1521</ymin>
			<xmax>371</xmax>
			<ymax>1577</ymax>
		</bndbox>
	</object>
	<object>
		<name>WF</name>
		<pose>Unspecified</pose>
		<truncated>0</truncated>
		<difficult>0</difficult>
		<bndbox>
			<xmin>1323</xmin>
			<ymin>1427</ymin>
			<xmax>1396</xmax>
			<ymax>1488</ymax>
		</bndbox>
	</object>
	<object>
		<name>WF</name>
		<pose>Unspecified</pose>
		<truncated>0</truncated>
		<difficult>0</difficult>
		<bndbox>
			<xmin>1521</xmin>
			<ymin>1582</ymin>
			<xmax>1584</xmax>
			<ymax>1637</ymax>
		</bndbox>
	</object>
	<object>
		<name>WF</name>
		<pose>Unspecified</pose>
		<truncated>0</truncated>
		<difficult>0</difficult>
		<bndbox>
			<xmin>1640</xmin>
			<ymin>1576</ymin>
			<xmax>1696</xmax>
			<ymax>1645</ymax>
		</bndbox>
	</object>
	<object>
		<name>WF</name>
		<pose>Unspecified</pose>
		<truncated>0</truncated>
		<difficult>0</difficult>
		<bndbox>
			<xmin>1923</xmin>
			<ymin>1273</ymin>
			<xmax>1993</xmax>
			<ymax>1335</ymax>
		</bndbox>
	</object>
	<object>
		<name>WF</name>
		<pose>Unspecified</pose>
		<truncated>0</truncated>
		<difficult>0</difficult>
		<bndbox>
			<xmin>3431</xmin>
			<ymin>1328</ymin>
			<xmax>3471</xmax>
			<ymax>1367</ymax>
		</bndbox>
	</object>
	<object>
		<name>WF</name>
		<pose>Unspecified</pose>
		<truncated>0</truncated>
		<difficult>0</difficult>
		<bndbox>
			<xmin>4062</xmin>
			<ymin>2294</ymin>
			<xmax>4108</xmax>
			<ymax>2331</ymax>
		</bndbox>
	</object>
	<object>
		<name>WF</name>
		<pose>Unspecified</pose>
		<truncated>0</truncated>
		<difficult>0</difficult>
		<bndbox>
			<xmin>4080</xmin>
			<ymin>2270</ymin>
			<xmax>4120</xmax>
			<ymax>2306</ymax>
		</bndbox>
	</object>
	<object>
		<name>WF</name>
		<pose>Unspecified</pose>
		<truncated>0</truncated>
		<difficult>0</difficult>
		<bndbox>
			<xmin>4159</xmin>
			<ymin>2213</ymin>
			<xmax>4224</xmax>
			<ymax>2263</ymax>
		</bndbox>
	</object>
	<object>
		<name>WF</name>
		<pose>Unspecified</pose>
		<truncated>0</truncated>
		<difficult>0</difficult>
		<bndbox>
			<xmin>4812</xmin>
			<ymin>2744</ymin>
			<xmax>4857</xmax>
			<ymax>2808</ymax>
		</bndbox>
	</object>
	<object>
		<name>WF</name>
		<pose>Unspecified</pose>
		<truncated>0</truncated>
		<difficult>0</difficult>
		<bndbox>
			<xmin>4359</xmin>
			<ymin>2899</ymin>
			<xmax>4411</xmax>
			<ymax>2951</ymax>
		</bndbox>
	</object>
	<object>
		<name>WF</name>
		<pose>Unspecified</pose>
		<truncated>0</truncated>
		<difficult>0</difficult>
		<bndbox>
			<xmin>1127</xmin>
			<ymin>1763</ymin>
			<xmax>1175</xmax>
			<ymax>1803</ymax>
		</bndbox>
	</object>
	<object>
		<name>WF</name>
		<pose>Unspecified</pose>
		<truncated>0</truncated>
		<difficult>0</difficult>
		<bndbox>
			<xmin>423</xmin>
			<ymin>2749</ymin>
			<xmax>449</xmax>
			<ymax>2779</ymax>
		</bndbox>
	</object>
	<object>
		<name>WF</name>
		<pose>Unspecified</pose>
		<truncated>0</truncated>
		<difficult>0</difficult>
		<bndbox>
			<xmin>4290</xmin>
			<ymin>825</ymin>
			<xmax>4331</xmax>
			<ymax>865</ymax>
		</bndbox>
	</object>
	<object>
		<name>WF</name>
		<pose>Unspecified</pose>
		<truncated>0</truncated>
		<difficult>0</difficult>
		<bndbox>
			<xmin>3636</xmin>
			<ymin>588</ymin>
			<xmax>3673</xmax>
			<ymax>631</ymax>
		</bndbox>
	</object>
</annotation>